{
  "VocabLists" :
  [
    {
      "id": "1",
      "name": "HSK 1",
      "description": "HSK 1 vocab list",
      "vocab_cnt": "150",
      "vocabs_source_url": "https://internfury.github.io/shuohuameta/hsklists/hsk1.txt",
      "status": "DOWNLOAD",
      "update_date": "1606587896"
    },
    {
      "id": "2",
      "name": "HSK 2",
      "description": "HSK 2 vocab list",
      "vocab_cnt": "150",
      "vocabs_source_url": "https://internfury.github.io/shuohuameta/hsklists/hsk2.txt",
      "status": "DOWNLOAD",
      "update_date": "1606587896"
    },
    {
      "id": "3",
      "name": "HSK 3",
      "description": "HSK 3 vocab list",
      "vocab_cnt": "300",
      "vocabs_source_url": "https://internfury.github.io/shuohuameta/hsklists/hsk3.txt",
      "status": "DOWNLOAD",
      "update_date": "1606587896"
    }
  ]
}
